Metadata-Version: 2.2
Name: datasets
Version: 4.4.0
Summary: HuggingFace community-driven open-source library of datasets
Home-page: https://github.com/huggingface/datasets
Download-URL: https://github.com/huggingface/datasets/tags
Author: HuggingFace Inc.
Author-email: thomas@huggingface.co
License: Apache 2.0
Keywords: datasets machine learning datasets
Classifier: Development Status :: 5 - Production/Stable
Classifier: Intended Audience :: Developers
Classifier: Intended Audience :: Education
Classifier: Intended Audience :: Science/Research
Classifier: License :: OSI Approved :: Apache Software License
Classifier: Operating System :: OS Independent
Classifier: Programming Language :: Python :: 3
Classifier: Programming Language :: Python :: 3.9
Classifier: Programming Language :: Python :: 3.10
Classifier: Programming Language :: Python :: 3.11
Classifier: Programming Language :: Python :: 3.12
Classifier: Programming Language :: Python :: 3.13
Classifier: Programming Language :: Python :: 3.14
Classifier: Topic :: Scientific/Engineering :: Artificial Intelligence
Requires-Python: >=3.9.0
License-File: LICENSE
License-File: AUTHORS
Requires-Dist: filelock
Requires-Dist: numpy>=1.17
Requires-Dist: pyarrow>=21.0.0
Requires-Dist: dill<0.4.1,>=0.3.0
Requires-Dist: pandas
Requires-Dist: requests>=2.32.2
Requires-Dist: httpx<1.0.0
Requires-Dist: tqdm>=4.66.3
Requires-Dist: xxhash
Requires-Dist: multiprocess<0.70.19
Requires-Dist: fsspec[http]<=2025.10.0,>=2023.1.0
Requires-Dist: huggingface-hub<2.0,>=0.25.0
Requires-Dist: packaging
Requires-Dist: pyyaml>=5.1
Provides-Extra: audio
Requires-Dist: torchcodec>=0.6.0; extra == "audio"
Requires-Dist: torch>=2.8.0; extra == "audio"
Provides-Extra: vision
Requires-Dist: Pillow>=9.4.0; extra == "vision"
Provides-Extra: tensorflow
Requires-Dist: tensorflow>=2.6.0; extra == "tensorflow"
Provides-Extra: tensorflow-gpu
Requires-Dist: tensorflow>=2.6.0; extra == "tensorflow-gpu"
Provides-Extra: torch
Requires-Dist: torch; extra == "torch"
Provides-Extra: jax
Requires-Dist: jax>=0.3.14; extra == "jax"
Requires-Dist: jaxlib>=0.3.14; extra == "jax"
Provides-Extra: streaming
Provides-Extra: dev
Requires-Dist: numba>=0.56.4; python_version < "3.14" and extra == "dev"
Requires-Dist: absl-py; extra == "dev"
Requires-Dist: decorator; extra == "dev"
Requires-Dist: joblib<1.3.0; extra == "dev"
Requires-Dist: joblibspark; python_version < "3.14" and extra == "dev"
Requires-Dist: pytest; extra == "dev"
Requires-Dist: pytest-datadir; extra == "dev"
Requires-Dist: pytest-xdist; extra == "dev"
Requires-Dist: aiohttp; extra == "dev"
Requires-Dist: elasticsearch<8.0.0,>=7.17.12; extra == "dev"
Requires-Dist: faiss-cpu>=1.8.0.post1; extra == "dev"
Requires-Dist: h5py; extra == "dev"
Requires-Dist: jax>=0.3.14; sys_platform != "win32" and extra == "dev"
Requires-Dist: jaxlib>=0.3.14; sys_platform != "win32" and extra == "dev"
Requires-Dist: lz4; python_version < "3.14" and extra == "dev"
Requires-Dist: moto[server]; extra == "dev"
Requires-Dist: pyspark>=3.4; extra == "dev"
Requires-Dist: py7zr; extra == "dev"
Requires-Dist: rarfile>=4.0; extra == "dev"
Requires-Dist: sqlalchemy; extra == "dev"
Requires-Dist: protobuf<4.0.0; extra == "dev"
Requires-Dist: tensorflow>=2.6.0; (python_version < "3.10" and sys_platform != "win32") and extra == "dev"
Requires-Dist: tensorflow>=2.16.0; (python_version >= "3.10" and sys_platform != "win32" and python_version < "3.14") and extra == "dev"
Requires-Dist: tiktoken; extra == "dev"
Requires-Dist: torch>=2.8.0; extra == "dev"
Requires-Dist: torchdata; extra == "dev"
Requires-Dist: transformers>=4.42.0; extra == "dev"
Requires-Dist: zstandard; extra == "dev"
Requires-Dist: polars[timezone]>=0.20.0; extra == "dev"
Requires-Dist: Pillow>=9.4.0; extra == "dev"
Requires-Dist: torchcodec>=0.7.0; python_version < "3.14" and extra == "dev"
Requires-Dist: nibabel>=5.3.1; extra == "dev"
Requires-Dist: ruff>=0.3.0; extra == "dev"
Requires-Dist: transformers; extra == "dev"
Requires-Dist: torch; extra == "dev"
Requires-Dist: tensorflow>=2.6.0; extra == "dev"
Provides-Extra: tests
Requires-Dist: numba>=0.56.4; python_version < "3.14" and extra == "tests"
Requires-Dist: absl-py; extra == "tests"
Requires-Dist: decorator; extra == "tests"
Requires-Dist: joblib<1.3.0; extra == "tests"
Requires-Dist: joblibspark; python_version < "3.14" and extra == "tests"
Requires-Dist: pytest; extra == "tests"
Requires-Dist: pytest-datadir; extra == "tests"
Requires-Dist: pytest-xdist; extra == "tests"
Requires-Dist: aiohttp; extra == "tests"
Requires-Dist: elasticsearch<8.0.0,>=7.17.12; extra == "tests"
Requires-Dist: faiss-cpu>=1.8.0.post1; extra == "tests"
Requires-Dist: h5py; extra == "tests"
Requires-Dist: jax>=0.3.14; sys_platform != "win32" and extra == "tests"
Requires-Dist: jaxlib>=0.3.14; sys_platform != "win32" and extra == "tests"
Requires-Dist: lz4; python_version < "3.14" and extra == "tests"
Requires-Dist: moto[server]; extra == "tests"
Requires-Dist: pyspark>=3.4; extra == "tests"
Requires-Dist: py7zr; extra == "tests"
Requires-Dist: rarfile>=4.0; extra == "tests"
Requires-Dist: sqlalchemy; extra == "tests"
Requires-Dist: protobuf<4.0.0; extra == "tests"
Requires-Dist: tensorflow>=2.6.0; (python_version < "3.10" and sys_platform != "win32") and extra == "tests"
Requires-Dist: tensorflow>=2.16.0; (python_version >= "3.10" and sys_platform != "win32" and python_version < "3.14") and extra == "tests"
Requires-Dist: tiktoken; extra == "tests"
Requires-Dist: torch>=2.8.0; extra == "tests"
Requires-Dist: torchdata; extra == "tests"
Requires-Dist: transformers>=4.42.0; extra == "tests"
Requires-Dist: zstandard; extra == "tests"
Requires-Dist: polars[timezone]>=0.20.0; extra == "tests"
Requires-Dist: Pillow>=9.4.0; extra == "tests"
Requires-Dist: torchcodec>=0.7.0; python_version < "3.14" and extra == "tests"
Requires-Dist: nibabel>=5.3.1; extra == "tests"
Provides-Extra: tests-numpy2
Requires-Dist: numba>=0.56.4; python_version < "3.14" and extra == "tests-numpy2"
Requires-Dist: absl-py; extra == "tests-numpy2"
Requires-Dist: decorator; extra == "tests-numpy2"
Requires-Dist: joblib<1.3.0; extra == "tests-numpy2"
Requires-Dist: joblibspark; python_version < "3.14" and extra == "tests-numpy2"
Requires-Dist: pytest; extra == "tests-numpy2"
Requires-Dist: pytest-datadir; extra == "tests-numpy2"
Requires-Dist: pytest-xdist; extra == "tests-numpy2"
Requires-Dist: aiohttp; extra == "tests-numpy2"
Requires-Dist: elasticsearch<8.0.0,>=7.17.12; extra == "tests-numpy2"
Requires-Dist: h5py; extra == "tests-numpy2"
Requires-Dist: jax>=0.3.14; sys_platform != "win32" and extra == "tests-numpy2"
Requires-Dist: jaxlib>=0.3.14; sys_platform != "win32" and extra == "tests-numpy2"
Requires-Dist: lz4; python_version < "3.14" and extra == "tests-numpy2"
Requires-Dist: moto[server]; extra == "tests-numpy2"
Requires-Dist: pyspark>=3.4; extra == "tests-numpy2"
Requires-Dist: py7zr; extra == "tests-numpy2"
Requires-Dist: rarfile>=4.0; extra == "tests-numpy2"
Requires-Dist: sqlalchemy; extra == "tests-numpy2"
Requires-Dist: protobuf<4.0.0; extra == "tests-numpy2"
Requires-Dist: tiktoken; extra == "tests-numpy2"
Requires-Dist: torch>=2.8.0; extra == "tests-numpy2"
Requires-Dist: torchdata; extra == "tests-numpy2"
Requires-Dist: transformers>=4.42.0; extra == "tests-numpy2"
Requires-Dist: zstandard; extra == "tests-numpy2"
Requires-Dist: polars[timezone]>=0.20.0; extra == "tests-numpy2"
Requires-Dist: Pillow>=9.4.0; extra == "tests-numpy2"
Requires-Dist: torchcodec>=0.7.0; python_version < "3.14" and extra == "tests-numpy2"
Requires-Dist: nibabel>=5.3.1; extra == "tests-numpy2"
Provides-Extra: quality
Requires-Dist: ruff>=0.3.0; extra == "quality"
Provides-Extra: benchmarks
Requires-Dist: tensorflow==2.12.0; extra == "benchmarks"
Requires-Dist: torch==2.0.1; extra == "benchmarks"
Requires-Dist: transformers==4.30.1; extra == "benchmarks"
Provides-Extra: docs
Requires-Dist: transformers; extra == "docs"
Requires-Dist: torch; extra == "docs"
Requires-Dist: tensorflow>=2.6.0; extra == "docs"
Provides-Extra: pdfs
Requires-Dist: pdfplumber>=0.11.4; extra == "pdfs"
Provides-Extra: nibabel
Requires-Dist: nibabel>=5.3.2; extra == "nibabel"
Dynamic: author
Dynamic: author-email
Dynamic: classifier
Dynamic: description
Dynamic: description-content-type
Dynamic: download-url
Dynamic: home-page
Dynamic: keywords
Dynamic: license
Dynamic: provides-extra
Dynamic: requires-dist
Dynamic: requires-python
Dynamic: summary
